iflow_mcp_ai_hub_admin_finance_agent_mcp_server/__init__.py
iflow_mcp_ai_hub_admin_finance_agent_mcp_server/server.py
iflow_mcp_ai_hub_admin_finance_agent_mcp_server-0.1.1.dist-info/METADATA
iflow_mcp_ai_hub_admin_finance_agent_mcp_server-0.1.1.dist-info/WHEEL
iflow_mcp_ai_hub_admin_finance_agent_mcp_server-0.1.1.dist-info/entry_points.txt
iflow_mcp_ai_hub_admin_finance_agent_mcp_server-0.1.1.dist-info/top_level.txt
iflow_mcp_ai_hub_admin_finance_agent_mcp_server-0.1.1.dist-info/RECORD
