Metadata-Version: 2.4
Name: iflow-mcp-ai-hub-admin-finance-agent-mcp-server
Version: 0.1.1
Summary: Add your description here
Requires-Python: >=3.11
Requires-Dist: httpx>=0.28.1
Requires-Dist: mcp[cli]>=1.9.4
Requires-Dist: financeagent>=0.0.1
Requires-Dist: func_timeout>=4.3.5
